smart_loco/app.py
smart_loco/cli.py
smart_loco/client/llm.py
smart_loco/components/chat.py
smart_loco-0.1.0.dist-info/METADATA
smart_loco-0.1.0.dist-info/WHEEL
smart_loco-0.1.0.dist-info/entry_points.txt
smart_loco-0.1.0.dist-info/top_level.txt
smart_loco-0.1.0.dist-info/RECORD
