Metadata-Version: 2.2
Name: smart-loco
Version: 0.1.0
Summary: A Streamlit application to interact with local LLMs using Ollama APIs.
Author: Deepak
Requires-Python: >=3.10
Requires-Dist: streamlit>=1.41.0
